sslearn/__init__.py
sslearn/base.py
sslearn/restricted.py
sslearn/utils.py
sslearn/datasets/__init__.py
sslearn/datasets/_loader.py
sslearn/datasets/_preprocess.py
sslearn/datasets/_writer.py
sslearn/model_selection/__init__.py
sslearn/model_selection/_split.py
sslearn/subview/__init__.py
sslearn/subview/_subview.py
sslearn/wrapper/__init__.py
sslearn/wrapper/_co.py
sslearn/wrapper/_self.py
sslearn/wrapper/_tritraining.py
sslearn-1.1.0.dist-info/METADATA
sslearn-1.1.0.dist-info/WHEEL
sslearn-1.1.0.dist-info/top_level.txt
sslearn-1.1.0.dist-info/RECORD
