Metadata-Version: 2.4
Name: sslearn
Version: 1.1.0
Summary: A Python package for semi-supervised learning with scikit-learn
Home-page: https://github.com/jlgarridol/sslearn
Download-URL: https://github.com/jlgarridol/sslearn/archive/refs/tags/1.1.0.tar.gz
Author: José Luis Garrido-Labrador
Author-email: jlgarrido@ubu.es
License: new BSD
Classifier: Development Status :: 5 - Production/Stable
Classifier: Intended Audience :: Science/Research
Classifier: Topic :: Scientific/Engineering
Classifier: License :: OSI Approved :: BSD License
Classifier: Programming Language :: Python :: 3
Classifier: Programming Language :: Python :: 3.8
Classifier: Programming Language :: Python :: 3.9
Classifier: Programming Language :: Python :: 3.10
Classifier: Programming Language :: Python :: 3.11
Classifier: Programming Language :: Python :: 3.12
Classifier: Programming Language :: Python :: 3.13
Requires-Dist: joblib>=1.2.0
Requires-Dist: numpy>=1.23.3
Requires-Dist: pandas>=1.4.3
Requires-Dist: scikit_learn>=1.2.0
Requires-Dist: scipy>=1.10.1
Requires-Dist: statsmodels>=0.13.2
Dynamic: author
Dynamic: author-email
Dynamic: classifier
Dynamic: description
Dynamic: description-content-type
Dynamic: download-url
Dynamic: home-page
Dynamic: license
Dynamic: requires-dist
Dynamic: summary
